{
    "general_fle": [
        {
            "language": "英语",
            "explanation": "(standard form) to spit out; to blame, name of an organic compounds"
        }
    ],
    "general_pinyins": [
        "niè"
    ],
    "general_zhuyins": [
        "ㄋㄧㄝˋ"
    ],
    "general_radical": {
        "radical": "口",
        "non_radical_sn": "7",
        "total_sn": "10"
    },
    "general_stc": "",
    "general_ytz": [
        "㖕",
        "𠱫",
        "𠲗",
        "𥥖"
    ],
    "general_structure": "上下结构",
    "general_char_codes": {
        "char_code_unicode_bs": [
            "3596",
            "4143112251"
        ],
        "char_code_wubi": "ukf",
        "char_code_cangjie": "ytjr",
        "char_code_zhengma": "sej",
        "char_code_sijiao": "00604"
    },
    "general_unicode": "扩展A U+3596",
    "general_bs_code": "4143112251"
}