{
    "general_fle": [
        {
            "language": "英语",
            "explanation": "unable to meet, empty room"
        }
    ],
    "general_pinyins": [
        "mián"
    ],
    "general_zhuyins": [
        "ㄇㄧㄢˊ"
    ],
    "general_radical": {
        "radical": "宀",
        "non_radical_sn": "15",
        "total_sn": "18"
    },
    "general_stc": "",
    "general_ytz": [
        "𡫛"
    ],
    "general_structure": "上下结构",
    "general_char_codes": {
        "char_code_unicode_bs": [
            "3770",
            "445325111445344153"
        ],
        "char_code_wubi": "pthy",
        "char_code_cangjie": "jhus",
        "char_code_zhengma": "wdws",
        "char_code_sijiao": "30227"
    },
    "general_unicode": "扩展A U+3770",
    "general_bs_code": "445325111445344153"
}