{
    "general_pinyins": "",
    "general_zhuyins": "",
    "general_radical": {
        "radical": "弓",
        "non_radical_sn": "5",
        "total_sn": "8"
    },
    "general_stc": "",
    "general_ytz": "",
    "general_structure": "左右结构",
    "general_char_codes": {
        "char_code_unicode_bs": [
            "38B1",
            "51554234"
        ],
        "char_code_wubi": "xciy",
        "char_code_cangjie": "nif",
        "char_code_zhengma": "yzzk",
        "char_code_sijiao": "13290"
    },
    "general_unicode": "扩展A U+38B1",
    "general_bs_code": "51554234"
}