{
    "general_pinyins": "",
    "general_zhuyins": "",
    "general_radical": {
        "radical": "忄",
        "non_radical_sn": "13",
        "total_sn": "16"
    },
    "general_stc": "",
    "general_ytz": "",
    "general_structure": "左右结构",
    "general_char_codes": {
        "char_code_unicode_bs": [
            "3999",
            "4422511252144544"
        ],
        "char_code_wubi": "njmn",
        "char_code_cangjie": "pwbp",
        "char_code_zhengma": "ukzw",
        "char_code_sijiao": "96032"
    },
    "general_unicode": "扩展A U+3999",
    "general_bs_code": "4422511252144544"
}