{
    "general_fle": [
        {
            "language": "英语",
            "explanation": "(ancient form of 收) to receive what is due; to gather together, to harvest, to collect; to put away, to close, to bind, to restrain, to bring to the end, (same as 摎) entwined -- as branches of a tree; to tangle; to involve, to collaborate; to band together"
        }
    ],
    "general_pinyins": "",
    "general_zhuyins": "",
    "general_radical": {
        "radical": "扌",
        "non_radical_sn": "2",
        "total_sn": "5"
    },
    "general_stc": "",
    "general_ytz": [
        "摎",
        "收"
    ],
    "general_structure": "左右结构",
    "general_char_codes": {
        "char_code_unicode_bs": [
            "39C3",
            "12152"
        ],
        "char_code_wubi": "rnhh",
        "char_code_cangjie": "qvl",
        "char_code_zhengma": "dzi",
        "char_code_sijiao": "52000"
    },
    "general_unicode": "扩展A U+39C3",
    "general_bs_code": "12152"
}