{
    "general_fle": [
        {
            "language": "英语",
            "explanation": "a whetstone used to grind precious stone (jade; a gem)"
        }
    ],
    "general_pinyins": "",
    "general_zhuyins": "",
    "general_radical": {
        "radical": "石",
        "non_radical_sn": "15",
        "total_sn": "20"
    },
    "general_stc": "",
    "general_ytz": "",
    "general_structure": "左右结构",
    "general_char_codes": {
        "char_code_unicode_bs": [
            "40F4",
            "13251411125112132511"
        ],
        "char_code_wubi": "dyfj",
        "char_code_cangjie": "mryra",
        "char_code_zhengma": "gsbm",
        "char_code_sijiao": "14660"
    },
    "general_unicode": "扩展A U+40F4",
    "general_bs_code": "13251411125112132511"
}