{
    "general_fle": [
        {
            "language": "英语",
            "explanation": "words of anger; words of dislike or hate"
        }
    ],
    "general_pinyins": [
        "wèi"
    ],
    "general_zhuyins": [
        "ㄨㄟˋ"
    ],
    "general_radical": {
        "radical": "言",
        "non_radical_sn": "14",
        "total_sn": "21"
    },
    "general_stc": "",
    "general_ytz": "",
    "general_structure": "左右结构",
    "general_char_codes": {
        "char_code_unicode_bs": [
            "471C",
            "411125121451343425111"
        ],
        "char_code_wubi": "yhph",
        "char_code_cangjie": "yrybu",
        "char_code_zhengma": "siol",
        "char_code_sijiao": "01668"
    },
    "general_unicode": "扩展A U+471C",
    "general_bs_code": "411125121451343425111"
}