{
    "general_fle": [
        {
            "language": "英语",
            "explanation": "to melt, to sell, to fling a lance or a spear; to brandish spears as if they were flying"
        }
    ],
    "general_pinyins": [
        "mèng"
    ],
    "general_zhuyins": [
        "ㄇㄥˋ"
    ],
    "general_radical": {
        "radical": "釒",
        "non_radical_sn": "15",
        "total_sn": "23"
    },
    "general_stc": "",
    "general_ytz": [
        "𨨸"
    ],
    "general_structure": "左右结构",
    "general_char_codes": {
        "char_code_unicode_bs": [
            "4970",
            "34112341415251214251214"
        ],
        "char_code_wubi": "qynj",
        "char_code_cangjie": "cyvi",
        "char_code_zhengma": "psii",
        "char_code_sijiao": "80136"
    },
    "general_unicode": "扩展A U+4970",
    "general_bs_code": "34112341415251214251214"
}