{
    "general_fle": [
        {
            "language": "英语",
            "explanation": "the period from 1 to 3 a.m.; 2nd character of the 'branches'"
        }
    ],
    "general_pinyins": [
        "chǒu"
    ],
    "general_zhuyins": [
        "ㄔㄡˇ"
    ],
    "general_radical": {
        "radical": "一",
        "non_radical_sn": "3",
        "total_sn": "4"
    },
    "general_stc": "",
    "general_ytz": "",
    "general_structure": "上下结构",
    "general_char_codes": {
        "char_code_unicode_bs": [
            "4E12",
            "5341"
        ],
        "char_code_wubi": "vygf",
        "char_code_cangjie": "skm",
        "char_code_zhengma": "ydsa",
        "char_code_sijiao": "17102"
    },
    "general_unicode": "基本区 U+4E12",
    "general_bs_code": "5341"
}