{
    "general_fle": [
        {
            "language": "英语",
            "explanation": "take, receive, obtain; select"
        },
        {
            "language": "德语",
            "explanation": "abheben (Geld)​  (V)​,abholen  (V)​,einsetzen als, ausgehen von  (V)​,zeichnen  (V)"
        },
        {
            "language": "法语",
            "explanation": "prendre,retirer,reprendre,obtenir,recevoir,adopter,choisir"
        }
    ],
    "general_pinyins": [
        "qǔ"
    ],
    "general_zhuyins": [
        "ㄑㄩˇ"
    ],
    "general_radical": {
        "radical": "又",
        "non_radical_sn": "6",
        "total_sn": "8"
    },
    "general_stc": "",
    "general_ytz": [
        "娶"
    ],
    "general_structure": "左右结构",
    "general_char_codes": {
        "char_code_unicode_bs": [
            "53D6",
            "12211154"
        ],
        "char_code_wubi": "bcy",
        "char_code_cangjie": "sje",
        "char_code_zhengma": "cexs",
        "char_code_sijiao": "17440"
    },
    "general_unicode": "基本区 U+53D6",
    "general_bs_code": "12211154"
}