{
    "general_fle": [
        {
            "language": "英语",
            "explanation": "(Cant.) a lump; measure word"
        }
    ],
    "general_pinyins": [
        "huò"
    ],
    "general_zhuyins": [
        "ㄏㄨㄛˋ"
    ],
    "general_radical": {
        "radical": "口",
        "non_radical_sn": "17",
        "total_sn": "20"
    },
    "general_stc": "",
    "general_ytz": "",
    "general_structure": "左右结构",
    "general_char_codes": {
        "char_code_unicode_bs": [
            "56BF",
            "25112232411121321511"
        ],
        "char_code_wubi": "kawv|kawe",
        "char_code_cangjie": "rtox",
        "char_code_zhengma": "jenn",
        "char_code_sijiao": "64077"
    },
    "general_unicode": "基本区 U+56BF",
    "general_bs_code": "25112232411121321511"
}