{
    "general_pinyins": [
        "xūn"
    ],
    "general_zhuyins": [
        "ㄒㄩㄣ"
    ],
    "general_radical": {
        "radical": "土",
        "non_radical_sn": "17",
        "total_sn": "20"
    },
    "general_stc": "",
    "general_ytz": [
        "塤",
        "壎"
    ],
    "general_structure": "左右结构",
    "general_char_codes": {
        "char_code_unicode_bs": [
            "58E6",
            "12112225125132411121"
        ],
        "char_code_wubi": "faky",
        "char_code_cangjie": "gtrg",
        "char_code_zhengma": "bejn",
        "char_code_sijiao": "44115"
    },
    "general_unicode": "基本区 U+58E6",
    "general_bs_code": "12112225125132411121"
}