{
    "general_pinyins": [
        "chà"
    ],
    "general_zhuyins": [
        "ㄔㄚˋ"
    ],
    "general_radical": {
        "radical": "女",
        "non_radical_sn": "3",
        "total_sn": "6"
    },
    "general_stc": [
        "姹"
    ],
    "general_ytz": [
        "𠇊",
        "姹"
    ],
    "general_structure": "左右结构",
    "general_char_codes": {
        "char_code_unicode_bs": [
            "597C",
            "531315"
        ],
        "char_code_wubi": "vtan",
        "char_code_cangjie": "vhp",
        "char_code_zhengma": "zmmh",
        "char_code_sijiao": "42414"
    },
    "general_unicode": "基本区 U+597C",
    "general_bs_code": "531315"
}