{
    "general_fle": [
        {
            "language": "英语",
            "explanation": "broad, wide, extensive"
        },
        {
            "language": "德语",
            "explanation": "breit, umfangreich, weit reichend ,weit ,Radikal Nr. 53 = Schrägdach, Schutz, Unterschlupf, Unterbringung  (S)"
        },
        {
            "language": "法语",
            "explanation": "vaste,immense,nombreux"
        }
    ],
    "general_pinyins": [
        "guǎng"
    ],
    "general_zhuyins": [
        "ㄍㄨㄤˇ"
    ],
    "general_radical": {
        "radical": "广",
        "non_radical_sn": "11",
        "total_sn": "14"
    },
    "general_stc": [
        "广"
    ],
    "general_ytz": [
        "広",
        "广"
    ],
    "general_structure": "左上包围结构",
    "general_char_codes": {
        "char_code_unicode_bs": [
            "5EE3",
            "41312212512134"
        ],
        "char_code_wubi": "yamw|oamw",
        "char_code_cangjie": "itlc",
        "char_code_zhengma": "tg",
        "char_code_sijiao": "00286"
    },
    "general_unicode": "基本区 U+5EE3",
    "general_bs_code": "41312212512134"
}