{
    "general_fle": [
        {
            "language": "英语",
            "explanation": "should, ought to, must"
        }
    ],
    "general_pinyins": [
        "yīng",
        "yìng"
    ],
    "general_zhuyins": [
        "ㄧㄥ",
        "ㄧㄥˋ"
    ],
    "general_radical": {
        "radical": "心",
        "non_radical_sn": "3",
        "total_sn": "7"
    },
    "general_stc": "",
    "general_ytz": [
        "應"
    ],
    "general_structure": "左上包围结构",
    "general_char_codes": {
        "char_code_unicode_bs": [
            "5FDC",
            "4134544"
        ],
        "char_code_wubi": "yni|oni",
        "char_code_cangjie": "xxip",
        "char_code_zhengma": "tgwz",
        "char_code_sijiao": "00230"
    },
    "general_unicode": "基本区 U+5FDC",
    "general_bs_code": "4134544"
}