{
    "general_fle": [
        {
            "language": "英语",
            "explanation": "sincere, earnest, cordial"
        },
        {
            "language": "德语",
            "explanation": "ernst, gesetzt"
        },
        {
            "language": "法语",
            "explanation": "sincère"
        }
    ],
    "general_pinyins": [
        "kěn"
    ],
    "general_zhuyins": [
        "ㄎㄣˇ"
    ],
    "general_radical": {
        "radical": "心",
        "non_radical_sn": "6",
        "total_sn": "10"
    },
    "general_stc": [
        "懇"
    ],
    "general_ytz": [
        "懇",
        "貇",
        "𡓚",
        "𢡆",
        "𢢽",
        "𧩺"
    ],
    "general_structure": "上下结构",
    "general_char_codes": {
        "char_code_unicode_bs": [
            "6073",
            "5115344544"
        ],
        "char_code_wubi": "venu|vnu",
        "char_code_cangjie": "avp",
        "char_code_zhengma": "xowz",
        "char_code_sijiao": "77333"
    },
    "general_unicode": "基本区 U+6073",
    "general_bs_code": "5115344544"
}