{
    "general_fle": [
        {
            "language": "英语",
            "explanation": "sincerity, honesty; modest"
        },
        {
            "language": "德语",
            "explanation": "aufrichtig, ehrlich"
        },
        {
            "language": "法语",
            "explanation": "honnête"
        }
    ],
    "general_pinyins": [
        "què"
    ],
    "general_zhuyins": [
        "ㄑㄩㄝˋ"
    ],
    "general_radical": {
        "radical": "心",
        "non_radical_sn": "7",
        "total_sn": "11"
    },
    "general_stc": [
        "愨",
        "慤"
    ],
    "general_ytz": [
        "愨",
        "慤",
        "𢠛",
        "𢡱",
        "𢢢",
        "𢢿",
        "𢤶"
    ],
    "general_structure": "上下结构",
    "general_char_codes": {
        "char_code_unicode_bs": [
            "60AB",
            "12145354544"
        ],
        "char_code_wubi": "fpmn|fpwn",
        "char_code_cangjie": "gbhp",
        "char_code_zhengma": "bwqw",
        "char_code_sijiao": "40331"
    },
    "general_unicode": "基本区 U+60AB",
    "general_bs_code": "12145354544"
}