{
    "general_pinyins": [
        "ái",
        "zhú"
    ],
    "general_zhuyins": [
        "ㄞˊ",
        "ㄓㄨˊ"
    ],
    "general_radical": {
        "radical": "攴",
        "non_radical_sn": "10",
        "total_sn": "14"
    },
    "general_stc": "",
    "general_ytz": [
        "敳",
        "𣪱"
    ],
    "general_structure": "左右结构",
    "general_char_codes": {
        "char_code_unicode_bs": [
            "6571",
            "25212514312154"
        ],
        "char_code_wubi": "mgkc",
        "char_code_cangjie": "utye",
        "char_code_zhengma": "llix",
        "char_code_sijiao": "21147"
    },
    "general_unicode": "基本区 U+6571",
    "general_bs_code": "25212514312154"
}