{
    "general_fle": [
        {
            "language": "英语",
            "explanation": "fork of road; branching off"
        },
        {
            "language": "德语",
            "explanation": "abweichend, divergierend"
        },
        {
            "language": "法语",
            "explanation": "bifurcation,haut,escarpé,erroné"
        }
    ],
    "general_pinyins": [
        "qí"
    ],
    "general_zhuyins": [
        "ㄑㄧˊ"
    ],
    "general_radical": {
        "radical": "止",
        "non_radical_sn": "4",
        "total_sn": "8"
    },
    "general_stc": "",
    "general_ytz": [
        "岐",
        "䅩",
        "枝",
        "𣥖",
        "跂"
    ],
    "general_structure": "左右结构",
    "general_char_codes": {
        "char_code_unicode_bs": [
            "6B67",
            "21211254"
        ],
        "char_code_wubi": "hfcy",
        "char_code_cangjie": "ymje",
        "char_code_zhengma": "iiex",
        "char_code_sijiao": "24147"
    },
    "general_unicode": "基本区 U+6B67",
    "general_bs_code": "21211254"
}