{
    "general_fle": [
        {
            "language": "英语",
            "explanation": "net; deceive; libel; negative"
        },
        {
            "language": "德语",
            "explanation": "täuschen, jn. hinters Licht führen  (V)​,Wang  (Eig, Fam)​,kein; ohne; nicht"
        },
        {
            "language": "法语",
            "explanation": "filet,ne pas,en vain,tromper"
        }
    ],
    "general_pinyins": [
        "wǎng"
    ],
    "general_zhuyins": [
        "ㄨㄤˇ"
    ],
    "general_radical": {
        "radical": "冂",
        "non_radical_sn": "6",
        "total_sn": "8"
    },
    "general_stc": "",
    "general_ytz": [
        "網",
        "㒺",
        "誷",
        "𠔿",
        "𠕏",
        "𡦽",
        "𡧏",
        "𤣴",
        "𦉽",
        "𧧜",
        "𣥙",
        "𦉰"
    ],
    "general_structure": "半包围结构",
    "general_char_codes": {
        "char_code_unicode_bs": [
            "7F54",
            "25431415"
        ],
        "char_code_wubi": "muyn",
        "char_code_cangjie": "btyv",
        "char_code_zhengma": "ldus",
        "char_code_sijiao": "77220"
    },
    "general_unicode": "基本区 U+7F54",
    "general_bs_code": "25431415"
}