{
    "general_fle": [
        {
            "language": "英语",
            "explanation": "internal organs, viscera"
        }
    ],
    "general_pinyins": [
        "zàng"
    ],
    "general_zhuyins": [
        "ㄗㄤˋ"
    ],
    "general_radical": {
        "radical": "月",
        "non_radical_sn": "14",
        "total_sn": "18"
    },
    "general_stc": "",
    "general_ytz": [
        "臟"
    ],
    "general_structure": "左右结构",
    "general_char_codes": {
        "char_code_unicode_bs": [
            "81D3",
            "351112213125125534"
        ],
        "char_code_wubi": "eadt|eadh",
        "char_code_cangjie": "btis",
        "char_code_zhengma": "qehh",
        "char_code_sijiao": "74253"
    },
    "general_unicode": "基本区 U+81D3",
    "general_bs_code": "351112213125125534"
}