{
    "general_pinyins": [
        "lèi"
    ],
    "general_zhuyins": [
        "ㄌㄟˋ"
    ],
    "general_radical": {
        "radical": "艹",
        "non_radical_sn": "19",
        "total_sn": "22"
    },
    "general_stc": "",
    "general_ytz": "",
    "general_structure": "上下结构",
    "general_char_codes": {
        "char_code_unicode_bs": [
            "8631",
            "1224312341344132511134"
        ],
        "char_code_wubi": "aodm",
        "char_code_cangjie": "tfkc",
        "char_code_zhengma": "eusg",
        "char_code_sijiao": "44886"
    },
    "general_unicode": "基本区 U+8631",
    "general_bs_code": "1224312341344132511134"
}