{
    "general_pinyins": [
        "bì"
    ],
    "general_zhuyins": [
        "ㄅㄧˋ"
    ],
    "general_radical": {
        "radical": "衤",
        "non_radical_sn": "14",
        "total_sn": "19"
    },
    "general_stc": "",
    "general_ytz": "",
    "general_structure": "左右结构",
    "general_char_codes": {
        "char_code_unicode_bs": [
            "8963",
            "4523432511125121132"
        ],
        "char_code_wubi": "putj",
        "char_code_cangjie": "lhul",
        "char_code_zhengma": "wtan",
        "char_code_sijiao": "36221"
    },
    "general_unicode": "基本区 U+8963",
    "general_bs_code": "4523432511125121132"
}