{
    "general_fle": [
        {
            "language": "英语",
            "explanation": "collar; to expose"
        },
        {
            "language": "德语",
            "explanation": "darlegen, enthüllen"
        },
        {
            "language": "法语",
            "explanation": "col brodé,apparence"
        }
    ],
    "general_pinyins": [
        "bó"
    ],
    "general_zhuyins": [
        "ㄅㄛˊ"
    ],
    "general_radical": {
        "radical": "衤",
        "non_radical_sn": "15",
        "total_sn": "20"
    },
    "general_stc": "",
    "general_ytz": [
        "𦆿",
        "𧟊",
        "㬧"
    ],
    "general_structure": "左右结构",
    "general_char_codes": {
        "char_code_unicode_bs": [
            "896E",
            "45234251112213424134"
        ],
        "char_code_wubi": "puji",
        "char_code_cangjie": "late",
        "char_code_zhengma": "wtok",
        "char_code_sijiao": "36299"
    },
    "general_unicode": "基本区 U+896E",
    "general_bs_code": "45234251112213424134"
}