{
    "general_fle": [
        {
            "language": "英语",
            "explanation": "coins, money, wealth; (Cant.) 鏹水, sulfuric acid"
        },
        {
            "language": "德语",
            "explanation": "Geld  (S)"
        },
        {
            "language": "法语",
            "explanation": "acide sulfurique,(argent)​,chaîne de pièces de monnaie"
        }
    ],
    "general_pinyins": [
        "qiǎng",
        "qiāng"
    ],
    "general_zhuyins": [
        "ㄑㄧㄤˇ",
        "ㄑㄧㄤ"
    ],
    "general_radical": {
        "radical": "釒",
        "non_radical_sn": "12",
        "total_sn": "20"
    },
    "general_stc": [
        "镪"
    ],
    "general_ytz": [
        "繈",
        "镪"
    ],
    "general_structure": "左右结构",
    "general_char_codes": {
        "char_code_unicode_bs": [
            "93F9",
            "34112431515251251214"
        ],
        "char_code_wubi": "qxkj",
        "char_code_cangjie": "xcnri",
        "char_code_zhengma": "pyji",
        "char_code_sijiao": "86136"
    },
    "general_unicode": "基本区 U+93F9",
    "general_bs_code": "34112431515251251214"
}