{
    "general_pinyins": "",
    "general_zhuyins": "",
    "general_radical": {
        "radical": "丿",
        "non_radical_sn": "4",
        "total_sn": "5"
    },
    "general_stc": "",
    "general_ytz": [
        "風"
    ],
    "general_structure": "上包围结构",
    "general_char_codes": {
        "char_code_unicode_bs": [
            "200A1",
            "35112"
        ],
        "char_code_wubi": "mfhk",
        "char_code_cangjie": "hnq",
        "char_code_zhengma": "qdbi"
    },
    "general_unicode": "扩展B U+200A1",
    "general_bs_code": "35112"
}