{
    "general_pinyins": [
        "shèng"
    ],
    "general_zhuyins": [
        "ㄕㄥˋ"
    ],
    "general_radical": {
        "radical": "亠",
        "non_radical_sn": "10",
        "total_sn": "12"
    },
    "general_stc": "",
    "general_ytz": [
        "勝"
    ],
    "general_structure": "上中下结构",
    "general_char_codes": {
        "char_code_unicode_bs": [
            "2016B",
            "413434343435"
        ],
        "char_code_wubi": "yqqm",
        "char_code_cangjie": "ykkn",
        "char_code_zhengma": "sooq"
    },
    "general_unicode": "扩展B U+2016B",
    "general_bs_code": "413434343435"
}