{
    "general_pinyins": "",
    "general_zhuyins": "",
    "general_radical": {
        "radical": "亻",
        "non_radical_sn": "12",
        "total_sn": "14"
    },
    "general_stc": "",
    "general_ytz": "",
    "general_structure": "左右结构",
    "general_char_codes": {
        "char_code_unicode_bs": [
            "20395",
            "32231341212152"
        ],
        "char_code_wubi": "whth",
        "char_code_cangjie": "oloq",
        "char_code_zhengma": "niem"
    },
    "general_unicode": "扩展B U+20395",
    "general_bs_code": "32231341212152"
}