{
    "general_pinyins": "",
    "general_zhuyins": "",
    "general_radical": {
        "radical": "几",
        "non_radical_sn": "2",
        "total_sn": "4"
    },
    "general_stc": "",
    "general_ytz": "",
    "general_structure": "左下包围结构",
    "general_char_codes": {
        "char_code_unicode_bs": [
            "2062B",
            "3554"
        ],
        "char_code_wubi": "mci",
        "char_code_cangjie": "hne",
        "char_code_zhengma": "qdxs"
    },
    "general_unicode": "扩展B U+2062B",
    "general_bs_code": "3554"
}