{
    "general_pinyins": [
        "dā"
    ],
    "general_zhuyins": "",
    "general_radical": {
        "radical": "刂",
        "non_radical_sn": "10",
        "total_sn": "12"
    },
    "general_stc": "",
    "general_ytz": [
        "𨨹"
    ],
    "general_structure": "左右结构",
    "general_char_codes": {
        "char_code_unicode_bs": [
            "20788",
            "251154154122"
        ],
        "char_code_wubi": "jnjh",
        "char_code_cangjie": "amln",
        "char_code_zhengma": "kyyk"
    },
    "general_unicode": "扩展B U+20788",
    "general_bs_code": "251154154122"
}