{
    "general_pinyins": [
        "jiū"
    ],
    "general_zhuyins": "",
    "general_radical": {
        "radical": "力",
        "non_radical_sn": "2",
        "total_sn": "4"
    },
    "general_stc": "",
    "general_ytz": "",
    "general_structure": "左右结构",
    "general_char_codes": {
        "char_code_unicode_bs": [
            "20833",
            "5253"
        ],
        "char_code_wubi": "nhln",
        "char_code_cangjie": "vlks",
        "char_code_zhengma": "ziym"
    },
    "general_unicode": "扩展B U+20833",
    "general_bs_code": "5253"
}