{
    "general_pinyins": "",
    "general_zhuyins": "",
    "general_radical": {
        "radical": "力",
        "non_radical_sn": "10",
        "total_sn": "12"
    },
    "general_stc": "",
    "general_ytz": [
        "劵"
    ],
    "general_structure": "上下结构",
    "general_char_codes": {
        "char_code_unicode_bs": [
            "2088F",
            "343123413453"
        ],
        "char_code_wubi": "todl",
        "char_code_cangjie": "hdkks",
        "char_code_zhengma": "pfgy"
    },
    "general_unicode": "扩展B U+2088F",
    "general_bs_code": "343123413453"
}