{
    "general_pinyins": "",
    "general_zhuyins": "",
    "general_radical": {
        "radical": "口",
        "non_radical_sn": "17",
        "total_sn": "20"
    },
    "general_stc": "",
    "general_ytz": "",
    "general_structure": "左右结构",
    "general_char_codes": {
        "char_code_unicode_bs": [
            "21150",
            "13334454431112431251"
        ],
        "char_code_wubi": "awyk",
        "char_code_zhengma": "eouj"
    },
    "general_unicode": "扩展B U+21150",
    "general_bs_code": "13334454431112431251"
}