{
    "general_pinyins": "",
    "general_zhuyins": "",
    "general_radical": {
        "radical": "土",
        "non_radical_sn": "10",
        "total_sn": "13"
    },
    "general_stc": "",
    "general_ytz": "",
    "general_structure": "左右结构",
    "general_char_codes": {
        "char_code_unicode_bs": [
            "213E3",
            "1213251111344"
        ],
        "char_code_wubi": "fthd",
        "char_code_zhengma": "bngs"
    },
    "general_unicode": "扩展B U+213E3",
    "general_bs_code": "1213251111344"
}