{
    "general_pinyins": "",
    "general_zhuyins": "",
    "general_radical": {
        "radical": "土",
        "non_radical_sn": "12",
        "total_sn": "15"
    },
    "general_stc": "",
    "general_ytz": "",
    "general_structure": "左右结构",
    "general_char_codes": {
        "char_code_unicode_bs": [
            "2142F",
            "121131325111354"
        ],
        "char_code_wubi": "fddt",
        "char_code_zhengma": "bgnr"
    },
    "general_unicode": "扩展B U+2142F",
    "general_bs_code": "121131325111354"
}