{
    "general_pinyins": [
        "jī"
    ],
    "general_zhuyins": [
        "ㄐㄧ"
    ],
    "general_radical": {
        "radical": "尸",
        "non_radical_sn": "8",
        "total_sn": "11"
    },
    "general_stc": "",
    "general_ytz": [
        "屐"
    ],
    "general_structure": "左上包围结构",
    "general_char_codes": {
        "char_code_unicode_bs": [
            "21C86",
            "51352131254"
        ],
        "char_code_wubi": "nnhc",
        "char_code_cangjie": "svme",
        "char_code_zhengma": "xmex"
    },
    "general_unicode": "扩展B U+21C86",
    "general_bs_code": "51352131254"
}