{
    "general_pinyins": [
        "dàn"
    ],
    "general_zhuyins": "",
    "general_radical": {
        "radical": "弓",
        "non_radical_sn": "2",
        "total_sn": "5"
    },
    "general_stc": "",
    "general_ytz": "",
    "general_structure": "左右结构",
    "general_char_codes": {
        "char_code_unicode_bs": [
            "223AA",
            "51535"
        ],
        "char_code_wubi": "xmn",
        "char_code_cangjie": "nhn",
        "char_code_zhengma": "yzqd"
    },
    "general_unicode": "扩展B U+223AA",
    "general_bs_code": "51535"
}