{
    "general_pinyins": "",
    "general_zhuyins": "",
    "general_radical": {
        "radical": "弓",
        "non_radical_sn": "16",
        "total_sn": "19"
    },
    "general_stc": "",
    "general_ytz": "",
    "general_structure": "左中右结构",
    "general_char_codes": {
        "char_code_unicode_bs": [
            "22435",
            "5154111251251251214"
        ],
        "char_code_wubi": "xykj",
        "char_code_cangjie": "nyri",
        "char_code_zhengma": "yzzi"
    },
    "general_unicode": "扩展B U+22435",
    "general_bs_code": "5154111251251251214"
}