{
    "general_pinyins": "",
    "general_zhuyins": "",
    "general_radical": {
        "radical": "戈",
        "non_radical_sn": "12",
        "total_sn": "16"
    },
    "general_stc": "",
    "general_ytz": [
        "矰"
    ],
    "general_structure": "左右结构",
    "general_char_codes": {
        "char_code_unicode_bs": [
            "22A09",
            "4325243125111534"
        ],
        "char_code_wubi": "ulja",
        "char_code_cangjie": "cai",
        "char_code_zhengma": "udkh"
    },
    "general_unicode": "扩展B U+22A09",
    "general_bs_code": "4325243125111534"
}