{
    "general_pinyins": "",
    "general_zhuyins": "",
    "general_radical": {
        "radical": "攴",
        "non_radical_sn": "10",
        "total_sn": "14"
    },
    "general_stc": "",
    "general_ytz": [
        "倏"
    ],
    "general_structure": "左右结构",
    "general_char_codes": {
        "char_code_unicode_bs": [
            "22FC5",
            "32221542512121"
        ],
        "char_code_wubi": "whhh",
        "char_code_cangjie": "olym",
        "char_code_zhengma": "niji"
    },
    "general_unicode": "扩展B U+22FC5",
    "general_bs_code": "32221542512121"
}