{
    "general_pinyins": [
        "biāo"
    ],
    "general_zhuyins": "",
    "general_radical": {
        "radical": "氵",
        "non_radical_sn": "30",
        "total_sn": "33"
    },
    "general_stc": "",
    "general_ytz": [
        "滮"
    ],
    "general_structure": "左右结构",
    "general_char_codes": {
        "char_code_unicode_bs": [
            "24180",
            "441121125444412112544441211254444"
        ],
        "char_code_wubi": "iccc",
        "char_code_cangjie": "esff",
        "char_code_zhengma": "vccc"
    },
    "general_unicode": "扩展B U+24180",
    "general_bs_code": "441121125444412112544441211254444"
}