{
    "general_pinyins": "",
    "general_zhuyins": "",
    "general_radical": {
        "radical": "目",
        "non_radical_sn": "13",
        "total_sn": "18"
    },
    "general_stc": "",
    "general_ytz": [
        "𥌪"
    ],
    "general_structure": "左右结构",
    "general_char_codes": {
        "char_code_unicode_bs": [
            "252E2",
            "251111251112511134"
        ],
        "char_code_wubi": "hdhh",
        "char_code_cangjie": "bukbu",
        "char_code_zhengma": "lgll"
    },
    "general_unicode": "扩展B U+252E2",
    "general_bs_code": "251111251112511134"
}