{
    "general_pinyins": "",
    "general_zhuyins": "",
    "general_radical": {
        "radical": "石",
        "non_radical_sn": "12",
        "total_sn": "17"
    },
    "general_stc": "",
    "general_ytz": "",
    "general_structure": "左下包围结构",
    "general_char_codes": {
        "char_code_unicode_bs": [
            "25591",
            "51331151325153254"
        ],
        "char_code_wubi": "ntfc",
        "char_code_zhengma": "xmgx"
    },
    "general_unicode": "扩展B U+25591",
    "general_bs_code": "51331151325153254"
}