{
    "general_pinyins": "",
    "general_zhuyins": "",
    "general_radical": {
        "radical": "米",
        "non_radical_sn": "17",
        "total_sn": "23"
    },
    "general_stc": "",
    "general_ytz": [
        "𥾂"
    ],
    "general_structure": "左右结构",
    "general_char_codes": {
        "char_code_unicode_bs": [
            "25F6E",
            "43123414524134515515515"
        ],
        "char_code_wubi": "ofxx",
        "char_code_cangjie": "fdmbn",
        "char_code_zhengma": "ufyy"
    },
    "general_unicode": "扩展B U+25F6E",
    "general_bs_code": "43123414524134515515515"
}