{
    "general_pinyins": "",
    "general_zhuyins": "",
    "general_radical": {
        "radical": "月",
        "non_radical_sn": "13",
        "total_sn": "17"
    },
    "general_stc": "",
    "general_ytz": "",
    "general_structure": "左右结构",
    "general_char_codes": {
        "char_code_unicode_bs": [
            "26881",
            "354112123415113251"
        ],
        "char_code_wubi": "eawk",
        "char_code_cangjie": "btor",
        "char_code_zhengma": "qexj"
    },
    "general_unicode": "扩展B U+26881",
    "general_bs_code": "354112123415113251"
}