{
    "general_pinyins": "",
    "general_zhuyins": "",
    "general_radical": {
        "radical": "虫",
        "non_radical_sn": "15",
        "total_sn": "21"
    },
    "general_stc": "",
    "general_ytz": [
        "蛭"
    ],
    "general_structure": "左右结构",
    "general_char_codes": {
        "char_code_unicode_bs": [
            "274F3",
            "251214331233122511134"
        ],
        "char_code_wubi": "jrrm",
        "char_code_cangjie": "lihlc",
        "char_code_zhengma": "ippl"
    },
    "general_unicode": "扩展B U+274F3",
    "general_bs_code": "251214331233122511134"
}