{
    "general_pinyins": "",
    "general_zhuyins": "",
    "general_radical": {
        "radical": "車",
        "non_radical_sn": "19",
        "total_sn": "26"
    },
    "general_stc": "",
    "general_ytz": [
        "𨎹"
    ],
    "general_structure": "左右结构",
    "general_char_codes": {
        "char_code_unicode_bs": [
            "283F8",
            "12511124125125125251111234"
        ],
        "char_code_wubi": "lyki",
        "char_code_cangjie": "jjyrf",
        "char_code_zhengma": "fkjb"
    },
    "general_unicode": "扩展B U+283F8",
    "general_bs_code": "12511124125125125251111234"
}