{
    "general_pinyins": [
        "luó"
    ],
    "general_zhuyins": [
        "ㄌㄨㄛˋ"
    ],
    "general_radical": {
        "radical": "魚",
        "non_radical_sn": "19",
        "total_sn": "30"
    },
    "general_stc": "",
    "general_ytz": "",
    "general_structure": "左右结构",
    "general_char_codes": {
        "char_code_unicode_bs": [
            "29F70",
            "352512144442522155444432411121"
        ],
        "char_code_wubi": "qoly",
        "char_code_cangjie": "nfwlg",
        "char_code_zhengma": "rlzn"
    },
    "general_unicode": "扩展B U+29F70",
    "general_bs_code": "352512144442522155444432411121"
}