{
    "general_pinyins": [
        "yáng"
    ],
    "general_zhuyins": "",
    "general_radical": {
        "radical": "鼠",
        "non_radical_sn": "9",
        "total_sn": "22"
    },
    "general_stc": "",
    "general_ytz": "",
    "general_structure": "左右结构",
    "general_char_codes": {
        "char_code_unicode_bs": [
            "2A56B",
            "3215115445445251113533"
        ],
        "char_code_wubi": "vnur",
        "char_code_cangjie": "hvamh",
        "char_code_zhengma": "nbro"
    },
    "general_unicode": "扩展B U+2A56B",
    "general_bs_code": "3215115445445251113533"
}