[
    {
        "pinyin": "zhàn",
        "pinyin_with_zhuyin": "zhàn   ㄓㄢˋ",
        "char_dict": [
            "表演。"
        ]
    },
    {
        "pinyin": "zhuàn",
        "pinyin_with_zhuyin": "zhuàn   ㄓㄨㄢˋ",
        "char_dict": [
            "应有。"
        ]
    },
    {
        "pinyin": "chán",
        "pinyin_with_zhuyin": "chán   ㄔㄢˊ",
        "char_dict": [
            "〔～僽（zhòu）〕ａ．烦恼；忧愁，如“唱道几处笙歌，几家～～”；ｂ．摧残；折磨，如“好花教风雨～～”；ｃ．责怪；埋怨，如“恐那人知后，把你～～”；ｄ．排谴，消闲，如“闲把诗～～”。"
        ],
        "word_phrase": [
            "僝僽"
        ]
    }
]