[
    {
        "pinyin": "yè",
        "pinyin_with_zhuyin": "yè  ㄧㄝˋ",
        "char_dict": [
            "植物的营养器官之一：树～。菜～。～子。～落归根。一～知秋。一～蔽目（喻目光短浅，常被眼前细小事物所遮蔽，看不到远处、大处。亦称“一叶障目”）。",
            "像叶子的：铁～。百～窗。",
            "同“页”。",
            "世代，时期：初～。末～。",
            "姓。"
        ],
        "word_phrase": [
            "叶斑病",
            "叶柄",
            "叶蜂",
            "叶公好龙",
            "叶红素",
            "叶猴",
            "叶黄素",
            "叶绿素",
            "叶轮",
            "叶落归根",
            "叶落知秋",
            "叶脉",
            "叶面",
            "叶片",
            "叶鞘",
            "叶肉",
            "叶酸",
            "叶甜菜",
            "叶序",
            "叶叶",
            "叶腋",
            "叶枝",
            "叶子"
        ]
    },
    {
        "pinyin": "xié",
        "pinyin_with_zhuyin": "xié  ㄒㄧㄝˊ",
        "char_dict": [
            "和洽，合：～韵。"
        ]
    }
]